telegram_error_logger/__init__.py
telegram_error_logger/main.py
telegram_error_logger/entities/__init__.py
telegram_error_logger/entities/error_message.py
telegram_error_logger/entities/log_level.py
telegram_error_logger/fastapi/__init__.py
telegram_error_logger/fastapi/exception_handler.py
telegram_error_logger/fastapi/middleware.py
telegram_error_logger/infrastructure/__init__.py
telegram_error_logger/infrastructure/error_formatter.py
telegram_error_logger/infrastructure/telegram_sender.py
telegram_error_logger/interfaces/__init__.py
telegram_error_logger/interfaces/error_formatter.py
telegram_error_logger/interfaces/message_sender.py
telegram_error_logger/use_cases/__init__.py
telegram_error_logger/use_cases/log_error.py
telegram_error_logger/use_cases/rate_limiter.py
fast_telegram_logger-0.1.0.dist-info/METADATA
fast_telegram_logger-0.1.0.dist-info/WHEEL
fast_telegram_logger-0.1.0.dist-info/top_level.txt
fast_telegram_logger-0.1.0.dist-info/RECORD
