Metadata-Version: 2.4
Name: fast-telegram-logger
Version: 0.1.0
Summary: Logging errors with subsequent sending to the telegram channel for FastAPI
Requires-Python: >=3.9
Requires-Dist: httpx>=0.28.1
Requires-Dist: pydantic>=2.11.7
